bumplot/__init__.py
bumplot/_utils.py
bumplot/bezier.py
bumplot/main.py
bumplot-0.1.1.dist-info/licenses/LICENSE
bumplot-0.1.1.dist-info/METADATA
bumplot-0.1.1.dist-info/WHEEL
bumplot-0.1.1.dist-info/top_level.txt
bumplot-0.1.1.dist-info/RECORD
