Metadata-Version: 2.4
Name: bumplot
Version: 0.1.1
Summary: Easily create and customize bump charts in Python
Author-email: Joseph Barbier <joseph.barbierdarnal@gmail.com>
License-Expression: MIT
Project-URL: Homepage, https://y-sunflower.github.io/bumplot/
Project-URL: Issues, https://github.com/y-sunflower/bumplot/issues
Project-URL: Documentation, https://y-sunflower.github.io/bumplot/
Project-URL: Repository, https://github.com/y-sunflower/bumplot
Keywords: bump,bump plot,bump charts,matplotlib,data,visualization,bezier,curve
Classifier: Programming Language :: Python :: 3
Classifier: Operating System :: OS Independent
Classifier: Development Status :: 4 - Beta
Requires-Python: >=3.10
License-File: LICENSE
Requires-Dist: matplotlib>=3.9.4
Requires-Dist: narwhals>=2.0.0
Dynamic: license-file
